subscribie/Template.py
subscribie/__init__.py
subscribie/auth.py
subscribie/bootstrap.py
subscribie/createdb.py
subscribie/db.py
subscribie/forms.py
subscribie/jamla.py
subscribie/signals.py
subscribie/symlink.py
subscribie/views.py
subscribie/blueprints/__init__.py
subscribie/blueprints/admin/__init__.py
subscribie-0.0.7.dist-info/LICENSE
subscribie-0.0.7.dist-info/METADATA
subscribie-0.0.7.dist-info/WHEEL
subscribie-0.0.7.dist-info/entry_points.txt
subscribie-0.0.7.dist-info/top_level.txt
subscribie-0.0.7.dist-info/RECORD
