Metadata-Version: 2.1
Name: subscribie
Version: 0.0.7
Summary: UNKNOWN
Home-page: UNKNOWN
Author: Karma Computing
Author-email: subscribie@karmacomputing.co.uk
License: UNKNOWN
Platform: UNKNOWN
Classifier: Programming Language :: Python :: 3
Classifier: License :: OSI Approved :: GNU Affero General Public License v3
Classifier: Operating System :: OS Independent
Requires-Dist: subscribiecli
Requires-Dist: Flask (<2,>=1)
Requires-Dist: flask-cors
Requires-Dist: flask-login
Requires-Dist: flask-uploads
Requires-Dist: flask-wtf
Requires-Dist: Flask-Mail (>=0.9.1)
Requires-Dist: requests
Requires-Dist: blinker
Requires-Dist: oauth2client
Requires-Dist: pyyaml
Requires-Dist: stripe
Requires-Dist: gocardless-pro
Requires-Dist: GitPython
